dictionary/__init__.py
dictionary/dictionary.py
ardaakcabuyuk_cs453_hw1_pipeline-2.0.0.dist-info/METADATA
ardaakcabuyuk_cs453_hw1_pipeline-2.0.0.dist-info/WHEEL
ardaakcabuyuk_cs453_hw1_pipeline-2.0.0.dist-info/top_level.txt
ardaakcabuyuk_cs453_hw1_pipeline-2.0.0.dist-info/RECORD
