Metadata-Version: 2.1
Name: ardaakcabuyuk-cs453-hw1-pipeline
Version: 2.0.0
Summary: UNKNOWN
Author: Arda Akça Büyük
License: UNKNOWN
Platform: UNKNOWN
Requires-Python: >=3.8
Requires-Dist: requests (>=2.23.0)
